[
{
  "id": 1,
  "name": "Артефакты",
  "type": "источник магии",
  "class_power": "E–Ω",
  "category": "материально-магический",
  "tags_base": [
    "материальная форма",
    "магическое ядро",
    "энергетическая печать",
    "доступны немагам",
    "стабильные эффекты"
  ],
  "tags_extended": [
    "божественное происхождение",
    "аномальное происхождение",
    "ремесленная магия",
    "ритуальные предметы",
    "источник силы",
    "передача энергии",
    "возможность связывания",
    "использование в ритуалах",
    "поглощение силы"
  ],
  "tags_high": [
    "Ω-артефакты",
    "пантеонные реликвии",
    "артефакты древних культур",
    "магические печати",
    "судебные артефакты",
    "предметы, меняющие ход истории"
  ],
  "small_card": {
    "name": "Артефакты",
    "rank": "источник магии",
    "type": "материально-магический",
    "aspect": "магия в плотской форме",
    "region": "встречаются повсюду",
    "use": "прямое, ритуальное, связанное",
    "danger": "C–S",
    "status": "основной и универсальный источник магии",
    "short": "Материальные предметы, в которых магия закреплена так же твердо, как металл или кость. Силу артефактов могут использовать даже немаги."
  },
  "big_card": {
    "title": "Артефакты — Своротки Силы",
    "description": "Материальные объекты, в которых магия не течет, а живет. Артефакты — самый универсальный источник силы: ими могут пользоваться даже те, кто не имеет природного дара. Сила предметов закреплена через печати, ритуалы, аномалии, пантеонные вмешательства или трагические события.",
    "structure": {
      "ядро": "Материальная форма: металл, камень, ткань, дерево, костяная выгравировка, лезвие-тень.",
      "печать": "Руническая, аномальная, судьбовая, временная, божественная или эмоциональная прошивка объекта.",
      "обрамление": "Аура, эффекты, свойства и реакции на владельца.",
      "личностная_реактивность": "Артефакт всегда по-своему реагирует на владельца: усиливает, ограничивает или трансформирует силу."
    },
    "usage": {
      "direct": "Предмет применяется напрямую: клинок режет тень, амулет гасит страх, маска усиливает слух.",
      "ritual": "Артефакт используется как часть ритуала: открывает путь, усиливает заклинание, связывает участника с духами.",
      "binding": "Связывание с владельцем через ритуал: сила усиливается, но побочные эффекты становятся постоянными.",
      "absorption": "Редкий и опасный метод: артефакт разрушается, а сила впитывается владельцем. Цена — изменение личности или судьбы.",
      "collective": "Некоторые артефакты раскрываются только при участии группы (3–7 человек)."
    },
    "classes": {
      "E_D": "Небольшие артефакты с базовыми эффектами. Часто используются охотниками и путниками.",
      "C_B": "Средне-сильные артефакты, семейные реликвии, предметы культа.",
      "A": "Редкие артефакты с серьезными боевыми или защитными свойствами.",
      "S": "Реликвии древних народов. Могут менять локальные события.",
      "Omega": "Связаны с пантеонами. Их сила — часть устройства мира."
    },
    "origins": [
      "создание мастеров-заклинателей",
      "божественные вмешательства",
      "аномальные зоны",
      "духи природы",
      "кристаллизация энергии",
      "кровь и жертвенные ритуалы",
      "отголоски великих войн или катастроф"
    ],
    "effects_on_world": [
      "формируют культы и религии",
      "становятся причиной войн и походов",
      "меняют историю регионов",
      "создают магические школы и ремесленные традиции",
      "используются героями и пантеонами",
      "накладывают скрытые последствия на окружающих"
    ]
  }
}
]
